moparsing/__init__.py
moparsing/instancemanager.py
moparsing/moparsing.py
tests/__init__.py
tests/conftest.py
tests/test_moparsing.py
parsingmo-0.1.0.dist-info/LICENSE
parsingmo-0.1.0.dist-info/METADATA
parsingmo-0.1.0.dist-info/WHEEL
parsingmo-0.1.0.dist-info/top_level.txt
parsingmo-0.1.0.dist-info/RECORD
