Metadata-Version: 2.1
Name: parsingmo
Version: 0.1.0
Summary: A simple tool to parse some MO files
Home-page: UNKNOWN
Author: A.Delaisement
License: MIT
Platform: UNKNOWN
Classifier: Programming Language :: Python :: 3.8
Classifier: Programming Language :: Python :: 3.9
Classifier: Programming Language :: Python :: 3.10
Classifier: Programming Language :: Python :: 3.11
Classifier: License :: OSI Approved :: MIT License
Classifier: Operating System :: OS Independent
Classifier: Topic :: Software Development :: Libraries :: Python Modules
Requires-Python: >=3.8
License-File: LICENSE
Provides-Extra: dev
Requires-Dist: wheel ; extra == 'dev'
Requires-Dist: black ; extra == 'dev'
Requires-Dist: pytest ; extra == 'dev'
Requires-Dist: mypy ; extra == 'dev'
